Workbook

Sheet Summary
A1: Sales Performance Report
A2: Consolidated from 3 source files | 01 Jan 2026 to 29 Jun 2026 | SAMPLE DATA: synthetic, for demonstration
A4: TOTAL REVENUE | B4: ORDERS | C4: UNITS SOLD | D4: AVG ORDER VALUE
A5: =SUM('Clean Data'!$J$2:$J$1273) -> 290929.32 | B5: =COUNTA('Clean Data'!$A$2:$A$1273) -> 1272 | C5: =SUM('Clean Data'!$G$2:$G$1273) -> 2990 | D5: =IF(B5=0,0,A5/B5) -> 228.71802
A7: Monthly trend
A8: Month | B8: Revenue ($) | C8: Orders | D8: Units | E8: Avg Order ($)
A9: 46023 | B9: =SUMIFS('Clean Data'!$J$2:$J$1273,'Clean Data'!$C$2:$C$1273,A9) -> 50703.34 | C9: =COUNTIFS('Clean Data'!$C$2:$C$1273,A9) -> 227 | D9: =SUMIFS('Clean Data'!$G$2:$G$1273,'Clean Data'!$C$2:$C$1273,A9) -> 530 | E9: =IF(C9=0,0,B9/C9) -> 223.36273
A10: 46054 | B10: =SUMIFS('Clean Data'!$J$2:$J$1273,'Clean Data'!$C$2:$C$1273,A10) -> 42870.03 | C10: =COUNTIFS('Clean Data'!$C$2:$C$1273,A10) -> 187 | D10: =SUMIFS('Clean Data'!$G$2:$G$1273,'Clean Data'!$C$2:$C$1273,A10) -> 442 | E10: =IF(C10=0,0,B10/C10) -> 229.2515
A11: 46082 | B11: =SUMIFS('Clean Data'!$J$2:$J$1273,'Clean Data'!$C$2:$C$1273,A11) -> 50074.96 | C11: =COUNTIFS('Clean Data'!$C$2:$C$1273,A11) -> 235 | D11: =SUMIFS('Clean Data'!$G$2:$G$1273,'Clean Data'!$C$2:$C$1273,A11) -> 561 | E11: =IF(C11=0,0,B11/C11) -> 213.08494
A12: 46113 | B12: =SUMIFS('Clean Data'!$J$2:$J$1273,'Clean Data'!$C$2:$C$1273,A12) -> 49884.67 | C12: =COUNTIFS('Clean Data'!$C$2:$C$1273,A12) -> 192 | D12: =SUMIFS('Clean Data'!$G$2:$G$1273,'Clean Data'!$C$2:$C$1273,A12) -> 469 | E12: =IF(C12=0,0,B12/C12) -> 259.81599
A13: 46143 | B13: =SUMIFS('Clean Data'!$J$2:$J$1273,'Clean Data'!$C$2:$C$1273,A13) -> 52511.66 | C13: =COUNTIFS('Clean Data'!$C$2:$C$1273,A13) -> 225 | D13: =SUMIFS('Clean Data'!$G$2:$G$1273,'Clean Data'!$C$2:$C$1273,A13) -> 512 | E13: =IF(C13=0,0,B13/C13) -> 233.38516
A14: 46174 | B14: =SUMIFS('Clean Data'!$J$2:$J$1273,'Clean Data'!$C$2:$C$1273,A14) -> 44884.66 | C14: =COUNTIFS('Clean Data'!$C$2:$C$1273,A14) -> 206 | D14: =SUMIFS('Clean Data'!$G$2:$G$1273,'Clean Data'!$C$2:$C$1273,A14) -> 476 | E14: =IF(C14=0,0,B14/C14) -> 217.8867
A15: Total | B15: =SUM(B9:B14) -> 290929.32 | C15: =SUM(C9:C14) -> 1272 | D15: =SUM(D9:D14) -> 2990 | E15: =IF(C15=0,0,B15/C15) -> 228.71802
A17: Revenue by product
A18: Product | B18: Units | C18: Revenue ($) | D18: % of Revenue
A19: Ergonomic Chair | B19: =SUMIFS('Clean Data'!$G$2:$G$1273,'Clean Data'!$E$2:$E$1273,A19) -> 263 | C19: =SUMIFS('Clean Data'!$J$2:$J$1273,'Clean Data'!$E$2:$E$1273,A19) -> 61516.36 | D19: =IF($A$5=0,0,C19/$A$5) -> 0.21144778
A20: 27-inch Monitor | B20: =SUMIFS('Clean Data'!$G$2:$G$1273,'Clean Data'!$E$2:$E$1273,A20) -> 275 | C20: =SUMIFS('Clean Data'!$J$2:$J$1273,'Clean Data'!$E$2:$E$1273,A20) -> 56830.88 | D20: =IF($A$5=0,0,C20/$A$5) -> 0.19534257
A21: Noise-Cancelling Headphones | B21: =SUMIFS('Clean Data'!$G$2:$G$1273,'Clean Data'!$E$2:$E$1273,A21) -> 314 | C21: =SUMIFS('Clean Data'!$J$2:$J$1273,'Clean Data'!$E$2:$E$1273,A21) -> 44743.09 | D21: =IF($A$5=0,0,C21/$A$5) -> 0.15379368
A22: Docking Station | B22: =SUMIFS('Clean Data'!$G$2:$G$1273,'Clean Data'!$E$2:$E$1273,A22) -> 231 | C22: =SUMIFS('Clean Data'!$J$2:$J$1273,'Clean Data'!$E$2:$E$1273,A22) -> 28319.55 | D22: =IF($A$5=0,0,C22/$A$5) -> 0.097341684
A23: Mechanical Keyboard | B23: =SUMIFS('Clean Data'!$G$2:$G$1273,'Clean Data'!$E$2:$E$1273,A23) -> 277 | C23: =SUMIFS('Clean Data'!$J$2:$J$1273,'Clean Data'!$E$2:$E$1273,A23) -> 23418.55 | D23: =IF($A$5=0,0,C23/$A$5) -> 0.080495668
A24: Bluetooth Speaker | B24: =SUMIFS('Clean Data'!$G$2:$G$1273,'Clean Data'!$E$2:$E$1273,A24) -> 271 | C24: =SUMIFS('Clean Data'!$J$2:$J$1273,'Clean Data'!$E$2:$E$1273,A24) -> 20386.07 | D24: =IF($A$5=0,0,C24/$A$5) -> 0.070072243
A25: External SSD 1TB | B25: =SUMIFS('Clean Data'!$G$2:$G$1273,'Clean Data'!$E$2:$E$1273,A25) -> 212 | C25: =SUMIFS('Clean Data'!$J$2:$J$1273,'Clean Data'!$E$2:$E$1273,A25) -> 20341.43 | D25: =IF($A$5=0,0,C25/$A$5) -> 0.069918804
A26: Webcam HD | B26: =SUMIFS('Clean Data'!$G$2:$G$1273,'Clean Data'!$E$2:$E$1273,A26) -> 231 | C26: =SUMIFS('Clean Data'!$J$2:$J$1273,'Clean Data'!$E$2:$E$1273,A26) -> 13027.19 | D26: =IF($A$5=0,0,C26/$A$5) -> 0.044777852
A27: Laptop Stand | B27: =SUMIFS('Clean Data'!$G$2:$G$1273,'Clean Data'!$E$2:$E$1273,A27) -> 264 | C27: =SUMIFS('Clean Data'!$J$2:$J$1273,'Clean Data'!$E$2:$E$1273,A27) -> 8665.98 | D27: =IF($A$5=0,0,C27/$A$5) -> 0.029787235
A28: Smart LED Lamp | B28: =SUMIFS('Clean Data'!$G$2:$G$1273,'Clean Data'!$E$2:$E$1273,A28) -> 205 | C28: =SUMIFS('Clean Data'!$J$2:$J$1273,'Clean Data'!$E$2:$E$1273,A28) -> 5866.95 | D28: =IF($A$5=0,0,C28/$A$5) -> 0.020166238
A29: Wireless Mouse | B29: =SUMIFS('Clean Data'!$G$2:$G$1273,'Clean Data'!$E$2:$E$1273,A29) -> 214 | C29: =SUMIFS('Clean Data'!$J$2:$J$1273,'Clean Data'!$E$2:$E$1273,A29) -> 4941.57 | D29: =IF($A$5=0,0,C29/$A$5) -> 0.016985466
A30: USB-C Cable | B30: =SUMIFS('Clean Data'!$G$2:$G$1273,'Clean Data'!$E$2:$E$1273,A30) -> 233 | C30: =SUMIFS('Clean Data'!$J$2:$J$1273,'Clean Data'!$E$2:$E$1273,A30) -> 2871.7 | D30: =IF($A$5=0,0,C30/$A$5) -> 0.0098707824
A32: Revenue by channel
A33: Channel | B33: Orders | C33: Revenue ($) | D33: % of Revenue
A34: In-Store | B34: =COUNTIFS('Clean Data'!$F$2:$F$1273,A34) -> 763 | C34: =SUMIFS('Clean Data'!$J$2:$J$1273,'Clean Data'!$F$2:$F$1273,A34) -> 173401.76 | D34: =IF($A$5=0,0,C34/$A$5) -> 0.5960271
A35: Online | B35: =COUNTIFS('Clean Data'!$F$2:$F$1273,A35) -> 509 | C35: =SUMIFS('Clean Data'!$J$2:$J$1273,'Clean Data'!$F$2:$F$1273,A35) -> 117527.56 | D35: =IF($A$5=0,0,C35/$A$5) -> 0.4039729
A38: Revenue = Quantity x Unit Price x (1 - Discount). All figures on this sheet are formulas over the Clean Data sheet.

Sheet Clean Data
A1: Order ID | B1: Order Date | C1: Month | D1: Customer | E1: Product | F1: Channel | G1: Quantity | H1: Unit Price | I1: Discount | J1: Revenue | K1: Source File
A2: S/7329 | B2: 46023 | C2: =DATE(YEAR(B2),MONTH(B2),1) -> 46023 | D2: Daniel Wilson | E2: External SSD 1TB | F2: In-Store | G2: 4 | H2: 96.28 | I2: 0.05 | J2: =ROUND(G2*H2*(1-I2),2) -> 365.86 | K2: south_store.xlsx
A3: S/7350 | B3: 46023 | C3: =DATE(YEAR(B3),MONTH(B3),1) -> 46023 | D3: Ethan Brown | E3: Ergonomic Chair | F3: In-Store | G3: 1 | H3: 252.44 | I3: 0.15 | J3: =ROUND(G3*H3*(1-I3),2) -> 214.57 | K3: south_store.xlsx
A4: W50204 | B4: 46023 | C4: =DATE(YEAR(B4),MONTH(B4),1) -> 46023 | D4: Olivia Butt | E4: Mechanical Keyboard | F4: Online | G4: 1 | H4: 88.07 | I4: 0 | J4: =ROUND(G4*H4*(1-I4),2) -> 88.07 | K4: online_shop.csv
A5: W50279 | B5: 46023 | C5: =DATE(YEAR(B5),MONTH(B5),1) -> 46023 | D5: Ali Raza | E5: Webcam HD | F5: Online | G5: 1 | H5: 59.02 | I5: 0 | J5: =ROUND(G5*H5*(1-I5),2) -> 59.02 | K5: online_shop.csv
A6: W50359 | B6: 46023 | C6: =DATE(YEAR(B6),MONTH(B6),1) -> 46023 | D6: Hassan Malik | E6: Wireless Mouse | F6: Online | G6: 4 | H6: 24.55 | I6: 0 | J6: =ROUND(G6*H6*(1-I6),2) -> 98.2 | K6: online_shop.csv
A7: W50393 | B7: 46023 | C7: =DATE(YEAR(B7),MONTH(B7),1) -> 46023 | D7: Chloe Raza | E7: External SSD 1TB | F7: Online | G7: 1 | H7: 101.89 | I7: 0.15 | J7: =ROUND(G7*H7*(1-I7),2) -> 86.61 | K7: online_shop.csv
A8: W50474 | B8: 46023 | C8: =DATE(YEAR(B8),MONTH(B8),1) -> 46023 | D8: Maya Sheikh | E8: Noise-Cancelling Headphones | F8: Online | G8: 2 | H8: 145.3 | I8: 0 | J8: =ROUND(G8*H8*(1-I8),2) -> 290.6 | K8: online_shop.csv
A9: N-1125 | B9: 46024 | C9: =DATE(YEAR(B9),MONTH(B9),1) -> 46023 | D9: Ethan Moore | E9: 27-inch Monitor | F9: In-Store | G9: 1 | H9: 215.13 | I9: 0 | J9: =ROUND(G9*H9*(1-I9),2) -> 215.13 | K9: north_store.csv
A10: N-1204 | B10: 46024 | C10: =DATE(YEAR(B10),MONTH(B10),1) -> 46023 | D10: Ayesha Raza | E10: Ergonomic Chair | F10: In-Store | G10: 2 | H10: 250.05 | I10: 0 | J10: =ROUND(G10*H10*(1-I10),2) -> 500.1 | K10: north_store.csv
A11: N-1216 | B11: 46024 | C11: =DATE(YEAR(B11),MONTH(B11),1) -> 46023 | D11: Hassan Iqbal | E11: USB-C Cable | F11: In-Store | G11: 1 | H11: 12.98 | I11: 0 | J11: =ROUND(G11*H11*(1-I11),2) -> 12.98 | K11: north_store.csv
A12: S/7014 | B12: 46024 | C12: =DATE(YEAR(B12),MONTH(B12),1) -> 46023 | D12: Olivia Hussain | E12: 27-inch Monitor | F12: In-Store | G12: 2 | H12: 222.93 | I12: 0.15 | J12: =ROUND(G12*H12*(1-I12),2) -> 378.98 | K12: south_store.xlsx
A13: S/7258 | B13: 46024 | C13: =DATE(YEAR(B13),MONTH(B13),1) -> 46023 | D13: Hannah Taylor | E13: Wireless Mouse | F13: In-Store | G13: 1 | H13: 24.22 | I13: 0.15 | J13: =ROUND(G13*H13*(1-I13),2) -> 20.59 | K13: south_store.xlsx
... A1273: W50262 | B1273: 46202 | C1273: =DATE(YEAR(B1273),MONTH(B1273),1) -> 46174 | D1273: Chloe Brown | E1273: 27-inch Monitor | F1273: Online | G1273: 1 | H1273: 219.47 | I1273: 0.05 | J1273: =ROUND(G1273*H1273*(1-I1273),2) -> 208.5 | K1273: online_shop.csv

Sheet Data Quality Log
A1: Data Quality Log
A2: What the pipeline found and fixed, with a row-count cross-check.
A4: Row-count cross-check
A5: Rows received (all source files) | B5: 1337
A6: Duplicate rows removed | B6: 37
A7: Rows rejected (see Rejected Rows sheet) | B7: 28
A8: Rows in Clean Data | B8: =COUNTA('Clean Data'!$A$2:$A$1273) -> 1272
A9: Difference (must be 0) | B9: =B5-B6-B7-B8 -> 0 | C9: =IF(B9=0,"OK - every row accounted for","CHECK") -> OK - every row accounted for
A11: Cleaning steps applied
A12: Check | B12: Rows / cells affected | C12: Action taken
A13: Column headers standardised across sources | B13: 19 | C13: Different names for the same field mapped to one schema
A14: Text trimmed (stray leading/trailing spaces) | B14: 649 | C14: Spaces removed from names, products and channels
A15: Product names standardised | B15: 373 | C15: Case, hyphen and spacing variants mapped to one product name
A16: Channel labels unified | B16: 1087 | C16: Web/web/WEB/Website -> Online; Store variants -> In-Store
A17: Dates converted to one format | B17: 528 | C17: Text dates in several formats parsed into real dates
A18: Prices cleaned | B18: 425 | C18: Currency symbols and thousands separators removed
A19: Discounts normalised to a decimal | B19: 604 | C19: '10%', 10 and 0.10 all become 0.10
A20: Quantities cleaned | B20: 12 | C20: Text such as '2 pcs' converted to the number 2
A21: Missing customer names filled | B21: 45 | C21: Set to 'Unknown' (kept, not dropped)
A22: Duplicate rows removed | B22: 37 | C22: Same order, date, product, quantity, price and discount

Sheet Rejected Rows
A1: Source | B1: Order ID | C1: Order Date (raw) | D1: Product (raw) | E1: Quantity (raw) | F1: Unit Price (raw) | G1: Reason
A2: north_store.csv | B2: N-1178 | C2: 12/02/2026 | D2: laptop stand | E2: 3 | G2: Missing or invalid unit price
A3: north_store.csv | B3: N-1114 | C3: 09/01/2026 | D3: Mechanical Keyboard | E3: -1 | F3: $86.33 | G3: Zero or negative quantity
A4: north_store.csv | B4: N-1170 | C4: 24/05/2026 | D4: USB-C Cable | E4: 0 | F4: $12.90 | G4: Zero or negative quantity
A5: north_store.csv | B5: N-1364 | C5: 23/01/2026 | D5: 27-INCH MONITOR | E5: 2 | G5: Missing or invalid unit price
A6: north_store.csv | B6: N-1241 | C6: 16/01/2026 | D6: Noise-Cancelling Headphones | E6: -1 | F6: $152.71 | G6: Zero or negative quantity
A7: north_store.csv | B7: N-1317 | C7: 07/03/2026 | D7: wireless mouse | E7: -1 | F7: $25.22 | G7: Zero or negative quantity
A8: north_store.csv | B8: N-1337 | C8: 12/04/2026 | D8: Ergonomic Chair | E8: -1 | F8: $251.90 | G8: Zero or negative quantity
A9: online_shop.csv | B9: W50232 | C9: 2026-03-31 | D9: Smart LED Lamp | E9: -1 | F9: 30.78 | G9: Zero or negative quantity
A10: online_shop.csv | B10: W50125 | C10: 2026-06-14 | D10: Wireless Mouse | E10: 1 | G10: Missing or invalid unit price
A11: online_shop.csv | B11: W50185 | C11: Jan 15, 2026 | D11: Mechanical Keyboard | E11: -1 | F11: 86.69 | G11: Zero or negative quantity
A12: online_shop.csv | B12: W50105 | C12: 2026-06-09 | D12: USB-C CABLE | E12: 0 | F12: 13.15 | G12: Zero or negative quantity
A13: online_shop.csv | B13: W50277 | C13: 2026-01-11 | D13: Docking Station | E13: 5 | G13: Missing or invalid unit price
A14: online_shop.csv | B14: W50066 | C14: 2026-02-23 | D14: Smart LED Lamp | E14: -1 | F14: 30.23 | G14: Zero or negative quantity
A15: online_shop.csv | B15: W50246 | C15: 2026-02-23 | D15: Laptop Stand | E15: 5 | G15: Missing or invalid unit price
A16: online_shop.csv | B16: W50182 | C16: 2026-04-29 | D16: Bluetooth Speaker | E16: 0 | F16: 79.89 | G16: Zero or negative quantity
A17: online_shop.csv | B17: W50100 | C17: Apr 25, 2026 | D17: Bluetooth Speaker | E17: 1 | G17: Missing or invalid unit price
A18: online_shop.csv | B18: W50412 | C18: 2026-05-19 | D18: External SSD 1TB | E18: 1 | G18: Missing or invalid unit price
A19: online_shop.csv | B19: W50401 | C19: 2026-02-28 | D19: Docking Station | E19: 2 | G19: Missing or invalid unit price
A20: south_store.xlsx | B20: S/7216 | C20: 2026-05-01 00:00:00 | D20: Wireless Mouse | E20: 2 | G20: Missing or invalid unit price
A21: south_store.xlsx | B21: S/7028 | C21: 2026-04-29 00:00:00 | D21: Smart LED Lamp | E21: 0 | F21: 30.79 | G21: Zero or negative quantity
A22: south_store.xlsx | B22: S/7111 | C22: 2026-01-09 00:00:00 | D22: external ssd 1tb | E22: 3 | G22: Missing or invalid unit price
A23: south_store.xlsx | B23: S/7226 | C23: 2026-01-15 00:00:00 | D23: External SSD 1TB | E23: -1 | F23: 99.94 | G23: Zero or negative quantity
A24: south_store.xlsx | B24: S/7239 | C24: 2026-01-04 00:00:00 | D24: Webcam HD | E24: 1 | G24: Missing or invalid unit price
A25: south_store.xlsx | B25: S/7306 | C25: 2026-03-28 00:00:00 | D25: Bluetooth Speaker | E25: -1 | F25: 76.71 | G25: Zero or negative quantity
A26: south_store.xlsx | B26: S/7283 | C26: 2026-02-02 00:00:00 | D26: USB-C Cable | E26: 2 | G26: Missing or invalid unit price
A27: south_store.xlsx | B27: S/7008 | C27: 2026-05-14 00:00:00 | D27: MECHANICAL KEYBOARD | E27: 2 | G27: Missing or invalid unit price
A28: south_store.xlsx | B28: S/7347 | C28: 2026-06-20 00:00:00 | D28: Docking Station | E28: -1 | F28: 132.82 | G28: Zero or negative quantity
A29: south_store.xlsx | B29: S/7157 | C29: 2026-04-21 00:00:00 | D29: 27-inch Monitor | E29: 0 | F29: 214.55 | G29: Zero or negative quantity
